flowchart_visualizer/__init__.py
flowchart_visualizer/utils.py
flowchart_visualizer/management/__init__.py
flowchart_visualizer/management/commands/__init__.py
flowchart_visualizer/management/commands/generate_flowchart.py
django_flow_viz_toolkit-0.1.1.dist-info/LICENSE
django_flow_viz_toolkit-0.1.1.dist-info/METADATA
django_flow_viz_toolkit-0.1.1.dist-info/WHEEL
django_flow_viz_toolkit-0.1.1.dist-info/top_level.txt
django_flow_viz_toolkit-0.1.1.dist-info/RECORD
