Metadata-Version: 2.1
Name: django-flow-viz-toolkit
Version: 0.1.1
Summary: A tool to generate flowcharts for Django projects
Home-page: https://github.com/arifbd2221/django-flow-viz-toolkit
Author: Mohidul Hoque Arif
Author-email: mohidulhoque216@gmail.com
License: MIT
Keywords: django,flowchart,visualization,model relationships,django models,URL mapping,middleware visualization,signal visualization,graph generation,pygraphviz,Django management commands,process visualization,Django package,project visualization,Django tools,developer tools
Classifier: Development Status :: 3 - Alpha
Classifier: Framework :: Django
Classifier: License :: OSI Approved :: MIT License
Classifier: Programming Language :: Python :: 3
Classifier: Programming Language :: Python :: 3.7
Classifier: Programming Language :: Python :: 3.8
Classifier: Programming Language :: Python :: 3.9
Classifier: Topic :: Software Development :: Libraries :: Application Frameworks
Classifier: Intended Audience :: Developers
Requires-Python: >=3.7
License-File: LICENSE
Requires-Dist: Django <5.2,>=3.0
Requires-Dist: pygraphviz >=1.13
Requires-Dist: tqdm >=4.66.5
